__init__.py
async_queue/__init__.py
async_queue/queue_item.py
async_queue/task_queue.py
async_queue_manager-4.0.0.dist-info/LICENSE
async_queue_manager-4.0.0.dist-info/METADATA
async_queue_manager-4.0.0.dist-info/WHEEL
async_queue_manager-4.0.0.dist-info/top_level.txt
async_queue_manager-4.0.0.dist-info/RECORD
