Metadata-Version: 2.2
Name: async-queue-manager
Version: 4.0.0
Summary: Asynchronous Task Queue
Author-email: Ichinga Samuel <ichingasamuel@gmail.com>
Project-URL: Homepage, https://github.com/Ichinga-Samuel/taskqueue
Project-URL: Bug Tracker, https://github.com/Ichinga-Samuel/taskqueue/issues
Keywords: queue,asynchronous,concurrency,asyncio
Classifier: Programming Language :: Python :: 3
Classifier: License :: OSI Approved :: MIT License
Classifier: Operating System :: OS Independent
Requires-Python: >=3.10
License-File: LICENSE
